piwik_api/__init__.py
piwik_api/base.py
piwik_api/modules.py
piwik_api-0.1.2.dist-info/DESCRIPTION.rst
piwik_api-0.1.2.dist-info/METADATA
piwik_api-0.1.2.dist-info/RECORD
piwik_api-0.1.2.dist-info/WHEEL
piwik_api-0.1.2.dist-info/metadata.json
piwik_api-0.1.2.dist-info/top_level.txt
