Metadata-Version: 2.0
Name: piwik-api
Version: 0.1.2
Summary: Client library for the Piwik Reporting API
Home-page: https://github.com/antsar/piwik-api
Author: Anton Sarukhanov
Author-email: code@ant.sr
License: MIT
Download-URL: https://github.com/antsar/piwik-api/archive/master.zip
Platform: UNKNOWN
Classifier: Development Status :: 4 - Beta
Classifier: Intended Audience :: Developers
Classifier: Environment :: Web Environment
Classifier: Environment :: Console
Classifier: License :: OSI Approved :: MIT License
Classifier: Natural Language :: English
Classifier: Programming Language :: Python
Classifier: Programming Language :: Python :: 3
Classifier: Programming Language :: Python :: 3.5
Requires-Dist: requests (==2.18.1)
